{
  "_fv": 24,
  "_type": "recipe",
  "definition": {
    "recipeType": "Crafting",
    "xpReward": 0.0,
    "cookingTime": 200,
    "recipeRetstackSize": 1,
    "group": "",
    "recipeShapeless": true,
    "recipeSlots": [
      {
        "value": "Blocks.WOOL"
      },
      {
        "value": "Items.STRING"
      },
      {
        "value": "Blocks.DIAMOND_BLOCK"
      },
      {
        "value": ""
      },
      {
        "value": ""
      },
      {
        "value": ""
      },
      {
        "value": ""
      },
      {
        "value": ""
      },
      {
        "value": ""
      }
    ],
    "recipeReturnStack": {
      "value": "CUSTOM:CummingArmor.legs"
    },
    "name": "cumming_armor_leggings_recipe",
    "namespace": "mod"
  }
}